{
  "path": "/library/meditron",
  "name": "meditron",
  "scraped_at": "2026-07-14T07:28:19.495922+00:00",
  "tags": [
    {
      "name": "latest",
      "size_bytes": 3800000000,
      "size_text": "3.8GB",
      "context": "2K",
      "input_type": "Text",
      "digest": "ad11a6250f54",
      "updated": "2 years ago",
      "format": "gguf",
      "usage_level": "",
      "usage_active_slots": 0
    },
    {
      "name": "7b",
      "size_bytes": 3800000000,
      "size_text": "3.8GB",
      "context": "2K",
      "input_type": "Text",
      "digest": "ad11a6250f54",
      "updated": "2 years ago",
      "format": "gguf",
      "usage_level": "",
      "usage_active_slots": 0
    },
    {
      "name": "70b",
      "size_bytes": 39000000000,
      "size_text": "39GB",
      "context": "4K",
      "input_type": "Text",
      "digest": "315d466c452f",
      "updated": "2 years ago",
      "format": "gguf",
      "usage_level": "",
      "usage_active_slots": 0
    },
    {
      "name": "7b-q2_K",
      "size_bytes": 2800000000,
      "size_text": "2.8GB",
      "context": "2K",
      "input_type": "Text",
      "digest": "f330bdb16b9e",
      "updated": "2 years ago",
      "format": "gguf",
      "usage_level": "",
      "usage_active_slots": 0
    },
    {
      "name": "7b-q3_K_S",
      "size_bytes": 2900000000,
      "size_text": "2.9GB",
      "context": "2K",
      "input_type": "Text",
      "digest": "6d5aa9319b05",
      "updated": "2 years ago",
      "format": "gguf",
      "usage_level": "",
      "usage_active_slots": 0
    },
    {
      "name": "7b-q3_K_M",
      "size_bytes": 3300000000,
      "size_text": "3.3GB",
      "context": "2K",
      "input_type": "Text",
      "digest": "9c9c4636a4b8",
      "updated": "2 years ago",
      "format": "gguf",
      "usage_level": "",
      "usage_active_slots": 0
    },
    {
      "name": "7b-q3_K_L",
      "size_bytes": 3600000000,
      "size_text": "3.6GB",
      "context": "2K",
      "input_type": "Text",
      "digest": "a6fa27f88bbc",
      "updated": "2 years ago",
      "format": "gguf",
      "usage_level": "",
      "usage_active_slots": 0
    },
    {
      "name": "7b-q4_0",
      "size_bytes": 3800000000,
      "size_text": "3.8GB",
      "context": "2K",
      "input_type": "Text",
      "digest": "ad11a6250f54",
      "updated": "2 years ago",
      "format": "gguf",
      "usage_level": "",
      "usage_active_slots": 0
    },
    {
      "name": "7b-q4_1",
      "size_bytes": 4200000000,
      "size_text": "4.2GB",
      "context": "2K",
      "input_type": "Text",
      "digest": "876165f9f2df",
      "updated": "2 years ago",
      "format": "gguf",
      "usage_level": "",
      "usage_active_slots": 0
    },
    {
      "name": "7b-q4_K_S",
      "size_bytes": 3900000000,
      "size_text": "3.9GB",
      "context": "2K",
      "input_type": "Text",
      "digest": "615f994626bd",
      "updated": "2 years ago",
      "format": "gguf",
      "usage_level": "",
      "usage_active_slots": 0
    },
    {
      "name": "7b-q4_K_M",
      "size_bytes": 4099999999,
      "size_text": "4.1GB",
      "context": "2K",
      "input_type": "Text",
      "digest": "a917f4ff62ba",
      "updated": "2 years ago",
      "format": "gguf",
      "usage_level": "",
      "usage_active_slots": 0
    },
    {
      "name": "7b-q5_0",
      "size_bytes": 4700000000,
      "size_text": "4.7GB",
      "context": "2K",
      "input_type": "Text",
      "digest": "79d156131358",
      "updated": "2 years ago",
      "format": "gguf",
      "usage_level": "",
      "usage_active_slots": 0
    },
    {
      "name": "7b-q5_1",
      "size_bytes": 5100000000,
      "size_text": "5.1GB",
      "context": "2K",
      "input_type": "Text",
      "digest": "04278d55ad3f",
      "updated": "2 years ago",
      "format": "gguf",
      "usage_level": "",
      "usage_active_slots": 0
    },
    {
      "name": "7b-q5_K_S",
      "size_bytes": 4700000000,
      "size_text": "4.7GB",
      "context": "2K",
      "input_type": "Text",
      "digest": "ff3d673fc3ab",
      "updated": "2 years ago",
      "format": "gguf",
      "usage_level": "",
      "usage_active_slots": 0
    },
    {
      "name": "7b-q5_K_M",
      "size_bytes": 4800000000,
      "size_text": "4.8GB",
      "context": "2K",
      "input_type": "Text",
      "digest": "1e91d442c62d",
      "updated": "2 years ago",
      "format": "gguf",
      "usage_level": "",
      "usage_active_slots": 0
    },
    {
      "name": "7b-q6_K",
      "size_bytes": 5500000000,
      "size_text": "5.5GB",
      "context": "2K",
      "input_type": "Text",
      "digest": "e98363fbb20a",
      "updated": "2 years ago",
      "format": "gguf",
      "usage_level": "",
      "usage_active_slots": 0
    },
    {
      "name": "7b-q8_0",
      "size_bytes": 7200000000,
      "size_text": "7.2GB",
      "context": "2K",
      "input_type": "Text",
      "digest": "902db8ed250b",
      "updated": "2 years ago",
      "format": "gguf",
      "usage_level": "",
      "usage_active_slots": 0
    },
    {
      "name": "7b-fp16",
      "size_bytes": 13000000000,
      "size_text": "13GB",
      "context": "2K",
      "input_type": "Text",
      "digest": "809731a3f1a9",
      "updated": "2 years ago",
      "format": "gguf",
      "usage_level": "",
      "usage_active_slots": 0
    },
    {
      "name": "70b-q4_0",
      "size_bytes": 39000000000,
      "size_text": "39GB",
      "context": "4K",
      "input_type": "Text",
      "digest": "315d466c452f",
      "updated": "2 years ago",
      "format": "gguf",
      "usage_level": "",
      "usage_active_slots": 0
    },
    {
      "name": "70b-q4_1",
      "size_bytes": 43000000000,
      "size_text": "43GB",
      "context": "4K",
      "input_type": "Text",
      "digest": "d0395a457ce6",
      "updated": "2 years ago",
      "format": "gguf",
      "usage_level": "",
      "usage_active_slots": 0
    },
    {
      "name": "70b-q4_K_S",
      "size_bytes": 39000000000,
      "size_text": "39GB",
      "context": "4K",
      "input_type": "Text",
      "digest": "4f8102818cd7",
      "updated": "2 years ago",
      "format": "gguf",
      "usage_level": "",
      "usage_active_slots": 0
    },
    {
      "name": "70b-q5_1",
      "size_bytes": 52000000000,
      "size_text": "52GB",
      "context": "4K",
      "input_type": "Text",
      "digest": "b12076361e76",
      "updated": "2 years ago",
      "format": "gguf",
      "usage_level": "",
      "usage_active_slots": 0
    }
  ]
}