{
  "applications": [],
  "cloud_context": "",
  "cloud_context_unit": "",
  "cloud_size": "",
  "cloud_size_unit": "",
  "cloud_usage_active_slots": 0,
  "cloud_usage_level": "",
  "files": [
    {
      "arch": "llama",
      "blob_url": "/huihui_ai/nemotron-v1-abliterated:latest/blobs/6f713abb22a3",
      "content_preview": "arch  llama",
      "parameters": "8.03B",
      "quantization": "Q4_K_M",
      "size": "4.9GB",
      "type": "model"
    },
    {
      "arch": "",
      "blob_url": "/huihui_ai/nemotron-v1-abliterated:latest/blobs/0ba8f0e314b4",
      "content_preview": "LLAMA 3.1 COMMUNITY LICENSE AGREEMENT\nLlama 3.1 Version Release Date: July 23, 2024\n“Agreement”",
      "parameters": "",
      "quantization": "",
      "size": "12kB",
      "type": "license"
    },
    {
      "arch": "",
      "blob_url": "/huihui_ai/nemotron-v1-abliterated:latest/blobs/13e31aa051d8",
      "content_preview": "{\n    \"stop\": [\n        \"<|start_header_id|>\",\n        \"<|end_header_id|>\",\n        \"<|eom_id|>\",",
      "parameters": "",
      "quantization": "",
      "size": "119B",
      "type": "params"
    },
    {
      "arch": "",
      "blob_url": "/huihui_ai/nemotron-v1-abliterated:latest/blobs/948af2743fc7",
      "content_preview": "{{- if or .System .Tools }}<|start_header_id|>system<|end_header_id|>\n{{- if .System }}\n{{ .System }",
      "parameters": "",
      "quantization": "",
      "size": "1.5kB",
      "type": "template"
    }
  ],
  "full_path": "/huihui_ai/nemotron-v1-abliterated:latest",
  "manifest_digest": "c60bac00af5f",
  "manifest_size": "4.9GB",
  "manifest_updated": "1 year ago",
  "path": "/huihui_ai/nemotron-v1-abliterated",
  "tag_name": "latest"
}