{
  "applications": [],
  "cloud_context": "",
  "cloud_context_unit": "",
  "cloud_size": "",
  "cloud_size_unit": "",
  "cloud_usage_active_slots": 0,
  "cloud_usage_level": "",
  "files": [
    {
      "arch": "llama",
      "blob_url": "/library/yi:9b-v1.5-fp16/blobs/72e4a665a7b3",
      "content_preview": "arch  llama",
      "parameters": "8.83B",
      "quantization": "F16",
      "size": "18GB",
      "type": "model"
    },
    {
      "arch": "",
      "blob_url": "/library/yi:9b-v1.5-fp16/blobs/c71d239df917",
      "content_preview": "Apache License\nVersion 2.0, January 2004\nhttp://www.apache.org/licenses/\nTERMS AND CONDITIONS FOR US",
      "parameters": "",
      "quantization": "",
      "size": "11kB",
      "type": "license"
    }
  ],
  "full_path": "/library/yi:9b-v1.5-fp16",
  "manifest_digest": "39f1635bfebb",
  "manifest_size": "18GB",
  "manifest_updated": "2 years ago",
  "path": "/library/yi",
  "scraped_at": "2026-07-13T20:30:37.494480+00:00",
  "tag_name": "9b-v1.5-fp16"
}