{
  "applications": [],
  "cloud_context": "",
  "cloud_context_unit": "",
  "cloud_size": "",
  "cloud_size_unit": "",
  "cloud_usage_active_slots": 0,
  "cloud_usage_level": "",
  "files": [
    {
      "arch": "llama",
      "blob_url": "/library/wizardcoder:33b-v1.1-fp16/blobs/84958c7d5017",
      "content_preview": "arch  llama",
      "parameters": "33.3B",
      "quantization": "F16",
      "size": "67GB",
      "type": "model"
    },
    {
      "arch": "",
      "blob_url": "/library/wizardcoder:33b-v1.1-fp16/blobs/876a8d805b60",
      "content_preview": "MICROSOFT RESEARCH LICENSE TERMS\nIF YOU LIVE IN THE UNITED STATES, PLEASE READ THE “BINDING ARBITR",
      "parameters": "",
      "quantization": "",
      "size": "10kB",
      "type": "license"
    },
    {
      "arch": "",
      "blob_url": "/library/wizardcoder:33b-v1.1-fp16/blobs/1678ff0c9fe5",
      "content_preview": "Below is an instruction that describes a task. Write a response that appropriately completes the req",
      "parameters": "",
      "quantization": "",
      "size": "105B",
      "type": "system"
    },
    {
      "arch": "",
      "blob_url": "/library/wizardcoder:33b-v1.1-fp16/blobs/2d836d77287d",
      "content_preview": "{{ .System }}\n### Instruction:\n{{ .Prompt }}\n### Response:",
      "parameters": "",
      "quantization": "",
      "size": "61B",
      "type": "template"
    }
  ],
  "full_path": "/library/wizardcoder:33b-v1.1-fp16",
  "manifest_digest": "a56de4864c5f",
  "manifest_size": "67GB",
  "manifest_updated": "2 years ago",
  "path": "/library/wizardcoder",
  "scraped_at": "2026-07-13T20:49:01.306639+00:00",
  "tag_name": "33b-v1.1-fp16"
}