{
  "name": "translategemma",
  "path": "/library/translategemma",
  "tags": [
    {
      "context": "128K",
      "digest": "c49d986b0764",
      "format": "gguf",
      "input_type": "Text, Image",
      "name": "latest",
      "size_bytes": 3300000000,
      "size_text": "3.3GB",
      "updated": "6 months ago",
      "usage_active_slots": 0,
      "usage_level": ""
    },
    {
      "context": "128K",
      "digest": "c49d986b0764",
      "format": "gguf",
      "input_type": "Text, Image",
      "name": "4b",
      "size_bytes": 3300000000,
      "size_text": "3.3GB",
      "updated": "6 months ago",
      "usage_active_slots": 0,
      "usage_level": ""
    },
    {
      "context": "128K",
      "digest": "c2f9a9ca1ec7",
      "format": "gguf",
      "input_type": "Text, Image",
      "name": "12b",
      "size_bytes": 8100000000,
      "size_text": "8.1GB",
      "updated": "6 months ago",
      "usage_active_slots": 0,
      "usage_level": ""
    },
    {
      "context": "128K",
      "digest": "21b597a243ec",
      "format": "gguf",
      "input_type": "Text, Image",
      "name": "27b",
      "size_bytes": 17000000000,
      "size_text": "17GB",
      "updated": "6 months ago",
      "usage_active_slots": 0,
      "usage_level": ""
    },
    {
      "context": "128K",
      "digest": "c49d986b0764",
      "format": "gguf",
      "input_type": "Text, Image",
      "name": "4b-it-q4_K_M",
      "size_bytes": 3300000000,
      "size_text": "3.3GB",
      "updated": "6 months ago",
      "usage_active_slots": 0,
      "usage_level": ""
    },
    {
      "context": "128K",
      "digest": "69729cbbfd35",
      "format": "gguf",
      "input_type": "Text, Image",
      "name": "4b-it-q8_0",
      "size_bytes": 4900000000,
      "size_text": "4.9GB",
      "updated": "6 months ago",
      "usage_active_slots": 0,
      "usage_level": ""
    },
    {
      "context": "128K",
      "digest": "ff7a6d70870f",
      "format": "gguf",
      "input_type": "Text, Image",
      "name": "4b-it-bf16",
      "size_bytes": 8600000000,
      "size_text": "8.6GB",
      "updated": "6 months ago",
      "usage_active_slots": 0,
      "usage_level": ""
    },
    {
      "context": "128K",
      "digest": "c2f9a9ca1ec7",
      "format": "gguf",
      "input_type": "Text, Image",
      "name": "12b-it-q4_K_M",
      "size_bytes": 8100000000,
      "size_text": "8.1GB",
      "updated": "6 months ago",
      "usage_active_slots": 0,
      "usage_level": ""
    },
    {
      "context": "128K",
      "digest": "48057379bc4d",
      "format": "gguf",
      "input_type": "Text, Image",
      "name": "12b-it-q8_0",
      "size_bytes": 13000000000,
      "size_text": "13GB",
      "updated": "6 months ago",
      "usage_active_slots": 0,
      "usage_level": ""
    },
    {
      "context": "128K",
      "digest": "7dc7429cc8b2",
      "format": "gguf",
      "input_type": "Text, Image",
      "name": "12b-it-bf16",
      "size_bytes": 24000000000,
      "size_text": "24GB",
      "updated": "6 months ago",
      "usage_active_slots": 0,
      "usage_level": ""
    },
    {
      "context": "128K",
      "digest": "21b597a243ec",
      "format": "gguf",
      "input_type": "Text, Image",
      "name": "27b-it-q4_K_M",
      "size_bytes": 17000000000,
      "size_text": "17GB",
      "updated": "6 months ago",
      "usage_active_slots": 0,
      "usage_level": ""
    },
    {
      "context": "128K",
      "digest": "b5b3e0d68687",
      "format": "gguf",
      "input_type": "Text, Image",
      "name": "27b-it-q8_0",
      "size_bytes": 30000000000,
      "size_text": "30GB",
      "updated": "6 months ago",
      "usage_active_slots": 0,
      "usage_level": ""
    },
    {
      "context": "128K",
      "digest": "0718798ae6f3",
      "format": "gguf",
      "input_type": "Text, Image",
      "name": "27b-it-bf16",
      "size_bytes": 55000000000,
      "size_text": "55GB",
      "updated": "6 months ago",
      "usage_active_slots": 0,
      "usage_level": ""
    }
  ]
}