{
  "path": "/library/codellama",
  "name": "codellama",
  "scraped_at": "2026-07-13T19:24:38.026177+00:00",
  "tags": [
    {
      "name": "latest",
      "size_bytes": 3800000000,
      "size_text": "3.8GB",
      "context": "16K",
      "input_type": "Text",
      "digest": "8fdf8f752f6e",
      "updated": "2 years ago",
      "format": "gguf",
      "usage_level": "",
      "usage_active_slots": 0
    },
    {
      "name": "code",
      "size_bytes": 3800000000,
      "size_text": "3.8GB",
      "context": "16K",
      "input_type": "Text",
      "digest": "8df0a30bb1e6",
      "updated": "1 year ago",
      "format": "gguf",
      "usage_level": "",
      "usage_active_slots": 0
    },
    {
      "name": "instruct",
      "size_bytes": 3800000000,
      "size_text": "3.8GB",
      "context": "16K",
      "input_type": "Text",
      "digest": "8fdf8f752f6e",
      "updated": "2 years ago",
      "format": "gguf",
      "usage_level": "",
      "usage_active_slots": 0
    },
    {
      "name": "python",
      "size_bytes": 3800000000,
      "size_text": "3.8GB",
      "context": "16K",
      "input_type": "Text",
      "digest": "120ca3419eae",
      "updated": "2 years ago",
      "format": "gguf",
      "usage_level": "",
      "usage_active_slots": 0
    },
    {
      "name": "7b",
      "size_bytes": 3800000000,
      "size_text": "3.8GB",
      "context": "16K",
      "input_type": "Text",
      "digest": "8fdf8f752f6e",
      "updated": "2 years ago",
      "format": "gguf",
      "usage_level": "",
      "usage_active_slots": 0
    },
    {
      "name": "13b",
      "size_bytes": 7400000000,
      "size_text": "7.4GB",
      "context": "16K",
      "input_type": "Text",
      "digest": "9f438cb9cd58",
      "updated": "2 years ago",
      "format": "gguf",
      "usage_level": "",
      "usage_active_slots": 0
    },
    {
      "name": "34b",
      "size_bytes": 19000000000,
      "size_text": "19GB",
      "context": "16K",
      "input_type": "Text",
      "digest": "685be00e1532",
      "updated": "2 years ago",
      "format": "gguf",
      "usage_level": "",
      "usage_active_slots": 0
    },
    {
      "name": "70b",
      "size_bytes": 39000000000,
      "size_text": "39GB",
      "context": "2K",
      "input_type": "Text",
      "digest": "e59b580dfce7",
      "updated": "2 years ago",
      "format": "gguf",
      "usage_level": "",
      "usage_active_slots": 0
    },
    {
      "name": "7b-code",
      "size_bytes": 3800000000,
      "size_text": "3.8GB",
      "context": "16K",
      "input_type": "Text",
      "digest": "8df0a30bb1e6",
      "updated": "1 year ago",
      "format": "gguf",
      "usage_level": "",
      "usage_active_slots": 0
    },
    {
      "name": "7b-code-q2_K",
      "size_bytes": 2800000000,
      "size_text": "2.8GB",
      "context": "16K",
      "input_type": "Text",
      "digest": "91ff9867e158",
      "updated": "1 year ago",
      "format": "gguf",
      "usage_level": "",
      "usage_active_slots": 0
    },
    {
      "name": "7b-code-q3_K_S",
      "size_bytes": 2900000000,
      "size_text": "2.9GB",
      "context": "16K",
      "input_type": "Text",
      "digest": "a53cf3fbfba9",
      "updated": "1 year ago",
      "format": "gguf",
      "usage_level": "",
      "usage_active_slots": 0
    },
    {
      "name": "7b-code-q3_K_M",
      "size_bytes": 3300000000,
      "size_text": "3.3GB",
      "context": "16K",
      "input_type": "Text",
      "digest": "feb1d9b1793b",
      "updated": "1 year ago",
      "format": "gguf",
      "usage_level": "",
      "usage_active_slots": 0
    },
    {
      "name": "7b-code-q3_K_L",
      "size_bytes": 3600000000,
      "size_text": "3.6GB",
      "context": "16K",
      "input_type": "Text",
      "digest": "28f2ce50aa95",
      "updated": "1 year ago",
      "format": "gguf",
      "usage_level": "",
      "usage_active_slots": 0
    },
    {
      "name": "7b-code-q4_0",
      "size_bytes": 3800000000,
      "size_text": "3.8GB",
      "context": "16K",
      "input_type": "Text",
      "digest": "8df0a30bb1e6",
      "updated": "1 year ago",
      "format": "gguf",
      "usage_level": "",
      "usage_active_slots": 0
    },
    {
      "name": "7b-code-q4_1",
      "size_bytes": 4200000000,
      "size_text": "4.2GB",
      "context": "16K",
      "input_type": "Text",
      "digest": "537584c9d430",
      "updated": "1 year ago",
      "format": "gguf",
      "usage_level": "",
      "usage_active_slots": 0
    },
    {
      "name": "7b-code-q4_K_S",
      "size_bytes": 3900000000,
      "size_text": "3.9GB",
      "context": "16K",
      "input_type": "Text",
      "digest": "87013da043fc",
      "updated": "1 year ago",
      "format": "gguf",
      "usage_level": "",
      "usage_active_slots": 0
    },
    {
      "name": "7b-code-q4_K_M",
      "size_bytes": 4099999999,
      "size_text": "4.1GB",
      "context": "16K",
      "input_type": "Text",
      "digest": "e0f44d809bb4",
      "updated": "1 year ago",
      "format": "gguf",
      "usage_level": "",
      "usage_active_slots": 0
    },
    {
      "name": "7b-code-q5_0",
      "size_bytes": 4700000000,
      "size_text": "4.7GB",
      "context": "16K",
      "input_type": "Text",
      "digest": "d7bab15b429c",
      "updated": "1 year ago",
      "format": "gguf",
      "usage_level": "",
      "usage_active_slots": 0
    },
    {
      "name": "7b-code-q5_1",
      "size_bytes": 5100000000,
      "size_text": "5.1GB",
      "context": "16K",
      "input_type": "Text",
      "digest": "a38c1ce2f694",
      "updated": "1 year ago",
      "format": "gguf",
      "usage_level": "",
      "usage_active_slots": 0
    },
    {
      "name": "7b-code-q5_K_S",
      "size_bytes": 4700000000,
      "size_text": "4.7GB",
      "context": "16K",
      "input_type": "Text",
      "digest": "1854c84f9cd6",
      "updated": "1 year ago",
      "format": "gguf",
      "usage_level": "",
      "usage_active_slots": 0
    },
    {
      "name": "7b-code-q5_K_M",
      "size_bytes": 4800000000,
      "size_text": "4.8GB",
      "context": "16K",
      "input_type": "Text",
      "digest": "19a534f2e7ca",
      "updated": "1 year ago",
      "format": "gguf",
      "usage_level": "",
      "usage_active_slots": 0
    },
    {
      "name": "7b-code-q6_K",
      "size_bytes": 5500000000,
      "size_text": "5.5GB",
      "context": "16K",
      "input_type": "Text",
      "digest": "e3d8d04437e4",
      "updated": "1 year ago",
      "format": "gguf",
      "usage_level": "",
      "usage_active_slots": 0
    },
    {
      "name": "7b-code-q8_0",
      "size_bytes": 7200000000,
      "size_text": "7.2GB",
      "context": "16K",
      "input_type": "Text",
      "digest": "b5c402bcc7d9",
      "updated": "1 year ago",
      "format": "gguf",
      "usage_level": "",
      "usage_active_slots": 0
    },
    {
      "name": "7b-code-fp16",
      "size_bytes": 13000000000,
      "size_text": "13GB",
      "context": "16K",
      "input_type": "Text",
      "digest": "49e540e808cb",
      "updated": "1 year ago",
      "format": "gguf",
      "usage_level": "",
      "usage_active_slots": 0
    },
    {
      "name": "7b-instruct",
      "size_bytes": 3800000000,
      "size_text": "3.8GB",
      "context": "16K",
      "input_type": "Text",
      "digest": "8fdf8f752f6e",
      "updated": "2 years ago",
      "format": "gguf",
      "usage_level": "",
      "usage_active_slots": 0
    },
    {
      "name": "7b-instruct-q2_K",
      "size_bytes": 2800000000,
      "size_text": "2.8GB",
      "context": "16K",
      "input_type": "Text",
      "digest": "28ee56afb6a5",
      "updated": "2 years ago",
      "format": "gguf",
      "usage_level": "",
      "usage_active_slots": 0
    },
    {
      "name": "7b-instruct-q3_K_S",
      "size_bytes": 2900000000,
      "size_text": "2.9GB",
      "context": "16K",
      "input_type": "Text",
      "digest": "69d540497dc3",
      "updated": "2 years ago",
      "format": "gguf",
      "usage_level": "",
      "usage_active_slots": 0
    },
    {
      "name": "7b-instruct-q3_K_M",
      "size_bytes": 3300000000,
      "size_text": "3.3GB",
      "context": "16K",
      "input_type": "Text",
      "digest": "ddae88ac7060",
      "updated": "2 years ago",
      "format": "gguf",
      "usage_level": "",
      "usage_active_slots": 0
    },
    {
      "name": "7b-instruct-q3_K_L",
      "size_bytes": 3600000000,
      "size_text": "3.6GB",
      "context": "16K",
      "input_type": "Text",
      "digest": "74aea2ff4240",
      "updated": "2 years ago",
      "format": "gguf",
      "usage_level": "",
      "usage_active_slots": 0
    },
    {
      "name": "7b-instruct-q4_0",
      "size_bytes": 3800000000,
      "size_text": "3.8GB",
      "context": "16K",
      "input_type": "Text",
      "digest": "8fdf8f752f6e",
      "updated": "2 years ago",
      "format": "gguf",
      "usage_level": "",
      "usage_active_slots": 0
    },
    {
      "name": "7b-instruct-q4_1",
      "size_bytes": 4200000000,
      "size_text": "4.2GB",
      "context": "16K",
      "input_type": "Text",
      "digest": "82177b511b42",
      "updated": "2 years ago",
      "format": "gguf",
      "usage_level": "",
      "usage_active_slots": 0
    },
    {
      "name": "7b-instruct-q4_K_S",
      "size_bytes": 3900000000,
      "size_text": "3.9GB",
      "context": "16K",
      "input_type": "Text",
      "digest": "7e7d9567e2be",
      "updated": "2 years ago",
      "format": "gguf",
      "usage_level": "",
      "usage_active_slots": 0
    },
    {
      "name": "7b-instruct-q4_K_M",
      "size_bytes": 4099999999,
      "size_text": "4.1GB",
      "context": "16K",
      "input_type": "Text",
      "digest": "dfd9bbf35961",
      "updated": "2 years ago",
      "format": "gguf",
      "usage_level": "",
      "usage_active_slots": 0
    },
    {
      "name": "7b-instruct-q5_0",
      "size_bytes": 4700000000,
      "size_text": "4.7GB",
      "context": "16K",
      "input_type": "Text",
      "digest": "1fe20720c90b",
      "updated": "2 years ago",
      "format": "gguf",
      "usage_level": "",
      "usage_active_slots": 0
    },
    {
      "name": "7b-instruct-q5_1",
      "size_bytes": 5100000000,
      "size_text": "5.1GB",
      "context": "16K",
      "input_type": "Text",
      "digest": "96ebcc6283ac",
      "updated": "2 years ago",
      "format": "gguf",
      "usage_level": "",
      "usage_active_slots": 0
    },
    {
      "name": "7b-instruct-q5_K_S",
      "size_bytes": 4700000000,
      "size_text": "4.7GB",
      "context": "16K",
      "input_type": "Text",
      "digest": "0a9dfb4ddb84",
      "updated": "2 years ago",
      "format": "gguf",
      "usage_level": "",
      "usage_active_slots": 0
    },
    {
      "name": "7b-instruct-q5_K_M",
      "size_bytes": 4800000000,
      "size_text": "4.8GB",
      "context": "16K",
      "input_type": "Text",
      "digest": "4f6dbd70addc",
      "updated": "2 years ago",
      "format": "gguf",
      "usage_level": "",
      "usage_active_slots": 0
    },
    {
      "name": "7b-instruct-q6_K",
      "size_bytes": 5500000000,
      "size_text": "5.5GB",
      "context": "16K",
      "input_type": "Text",
      "digest": "3a5b549ceb36",
      "updated": "2 years ago",
      "format": "gguf",
      "usage_level": "",
      "usage_active_slots": 0
    },
    {
      "name": "7b-instruct-q8_0",
      "size_bytes": 7200000000,
      "size_text": "7.2GB",
      "context": "16K",
      "input_type": "Text",
      "digest": "e371f415ddec",
      "updated": "2 years ago",
      "format": "gguf",
      "usage_level": "",
      "usage_active_slots": 0
    },
    {
      "name": "7b-instruct-fp16",
      "size_bytes": 13000000000,
      "size_text": "13GB",
      "context": "16K",
      "input_type": "Text",
      "digest": "6d0772f2d7d0",
      "updated": "2 years ago",
      "format": "gguf",
      "usage_level": "",
      "usage_active_slots": 0
    },
    {
      "name": "7b-python",
      "size_bytes": 3800000000,
      "size_text": "3.8GB",
      "context": "16K",
      "input_type": "Text",
      "digest": "120ca3419eae",
      "updated": "2 years ago",
      "format": "gguf",
      "usage_level": "",
      "usage_active_slots": 0
    },
    {
      "name": "7b-python-q2_K",
      "size_bytes": 2800000000,
      "size_text": "2.8GB",
      "context": "16K",
      "input_type": "Text",
      "digest": "90537ffccfc3",
      "updated": "2 years ago",
      "format": "gguf",
      "usage_level": "",
      "usage_active_slots": 0
    },
    {
      "name": "7b-python-q3_K_S",
      "size_bytes": 2900000000,
      "size_text": "2.9GB",
      "context": "16K",
      "input_type": "Text",
      "digest": "32abf4fb831c",
      "updated": "2 years ago",
      "format": "gguf",
      "usage_level": "",
      "usage_active_slots": 0
    },
    {
      "name": "7b-python-q3_K_M",
      "size_bytes": 3300000000,
      "size_text": "3.3GB",
      "context": "16K",
      "input_type": "Text",
      "digest": "f78512a1494b",
      "updated": "2 years ago",
      "format": "gguf",
      "usage_level": "",
      "usage_active_slots": 0
    },
    {
      "name": "7b-python-q3_K_L",
      "size_bytes": 3600000000,
      "size_text": "3.6GB",
      "context": "16K",
      "input_type": "Text",
      "digest": "89bd2bcbe688",
      "updated": "2 years ago",
      "format": "gguf",
      "usage_level": "",
      "usage_active_slots": 0
    },
    {
      "name": "7b-python-q4_0",
      "size_bytes": 3800000000,
      "size_text": "3.8GB",
      "context": "16K",
      "input_type": "Text",
      "digest": "120ca3419eae",
      "updated": "2 years ago",
      "format": "gguf",
      "usage_level": "",
      "usage_active_slots": 0
    },
    {
      "name": "7b-python-q4_1",
      "size_bytes": 4200000000,
      "size_text": "4.2GB",
      "context": "16K",
      "input_type": "Text",
      "digest": "229914b4c95a",
      "updated": "2 years ago",
      "format": "gguf",
      "usage_level": "",
      "usage_active_slots": 0
    },
    {
      "name": "7b-python-q4_K_S",
      "size_bytes": 3900000000,
      "size_text": "3.9GB",
      "context": "16K",
      "input_type": "Text",
      "digest": "3e2981f24208",
      "updated": "2 years ago",
      "format": "gguf",
      "usage_level": "",
      "usage_active_slots": 0
    },
    {
      "name": "7b-python-q4_K_M",
      "size_bytes": 4099999999,
      "size_text": "4.1GB",
      "context": "16K",
      "input_type": "Text",
      "digest": "82469243d8df",
      "updated": "2 years ago",
      "format": "gguf",
      "usage_level": "",
      "usage_active_slots": 0
    },
    {
      "name": "7b-python-q5_0",
      "size_bytes": 4700000000,
      "size_text": "4.7GB",
      "context": "16K",
      "input_type": "Text",
      "digest": "ca3bea54d322",
      "updated": "2 years ago",
      "format": "gguf",
      "usage_level": "",
      "usage_active_slots": 0
    },
    {
      "name": "7b-python-q5_1",
      "size_bytes": 5100000000,
      "size_text": "5.1GB",
      "context": "16K",
      "input_type": "Text",
      "digest": "973c0b9ff6f2",
      "updated": "2 years ago",
      "format": "gguf",
      "usage_level": "",
      "usage_active_slots": 0
    },
    {
      "name": "7b-python-q5_K_S",
      "size_bytes": 4700000000,
      "size_text": "4.7GB",
      "context": "16K",
      "input_type": "Text",
      "digest": "33d5fb72706b",
      "updated": "2 years ago",
      "format": "gguf",
      "usage_level": "",
      "usage_active_slots": 0
    },
    {
      "name": "7b-python-q5_K_M",
      "size_bytes": 4800000000,
      "size_text": "4.8GB",
      "context": "16K",
      "input_type": "Text",
      "digest": "cf2d34d45cf5",
      "updated": "2 years ago",
      "format": "gguf",
      "usage_level": "",
      "usage_active_slots": 0
    },
    {
      "name": "7b-python-q6_K",
      "size_bytes": 5500000000,
      "size_text": "5.5GB",
      "context": "16K",
      "input_type": "Text",
      "digest": "d03cee358f2e",
      "updated": "2 years ago",
      "format": "gguf",
      "usage_level": "",
      "usage_active_slots": 0
    },
    {
      "name": "7b-python-q8_0",
      "size_bytes": 7200000000,
      "size_text": "7.2GB",
      "context": "16K",
      "input_type": "Text",
      "digest": "9989aa9990d5",
      "updated": "2 years ago",
      "format": "gguf",
      "usage_level": "",
      "usage_active_slots": 0
    },
    {
      "name": "7b-python-fp16",
      "size_bytes": 13000000000,
      "size_text": "13GB",
      "context": "16K",
      "input_type": "Text",
      "digest": "c586d7593fc9",
      "updated": "2 years ago",
      "format": "gguf",
      "usage_level": "",
      "usage_active_slots": 0
    },
    {
      "name": "13b-code",
      "size_bytes": 7400000000,
      "size_text": "7.4GB",
      "context": "16K",
      "input_type": "Text",
      "digest": "61b6aa1b3d0f",
      "updated": "1 year ago",
      "format": "gguf",
      "usage_level": "",
      "usage_active_slots": 0
    },
    {
      "name": "13b-code-q2_K",
      "size_bytes": 5400000000,
      "size_text": "5.4GB",
      "context": "16K",
      "input_type": "Text",
      "digest": "15030cfe1222",
      "updated": "1 year ago",
      "format": "gguf",
      "usage_level": "",
      "usage_active_slots": 0
    },
    {
      "name": "13b-code-q3_K_S",
      "size_bytes": 5700000000,
      "size_text": "5.7GB",
      "context": "16K",
      "input_type": "Text",
      "digest": "19a8f7d27f99",
      "updated": "1 year ago",
      "format": "gguf",
      "usage_level": "",
      "usage_active_slots": 0
    },
    {
      "name": "13b-code-q3_K_M",
      "size_bytes": 6300000000,
      "size_text": "6.3GB",
      "context": "16K",
      "input_type": "Text",
      "digest": "89cf92af026f",
      "updated": "1 year ago",
      "format": "gguf",
      "usage_level": "",
      "usage_active_slots": 0
    },
    {
      "name": "13b-code-q3_K_L",
      "size_bytes": 6900000000,
      "size_text": "6.9GB",
      "context": "16K",
      "input_type": "Text",
      "digest": "ba5706a5838b",
      "updated": "1 year ago",
      "format": "gguf",
      "usage_level": "",
      "usage_active_slots": 0
    },
    {
      "name": "13b-code-q4_0",
      "size_bytes": 7400000000,
      "size_text": "7.4GB",
      "context": "16K",
      "input_type": "Text",
      "digest": "61b6aa1b3d0f",
      "updated": "1 year ago",
      "format": "gguf",
      "usage_level": "",
      "usage_active_slots": 0
    },
    {
      "name": "13b-code-q4_1",
      "size_bytes": 8199999999,
      "size_text": "8.2GB",
      "context": "16K",
      "input_type": "Text",
      "digest": "57327f6dcb54",
      "updated": "1 year ago",
      "format": "gguf",
      "usage_level": "",
      "usage_active_slots": 0
    },
    {
      "name": "13b-code-q4_K_S",
      "size_bytes": 7400000000,
      "size_text": "7.4GB",
      "context": "16K",
      "input_type": "Text",
      "digest": "87379a37e4aa",
      "updated": "1 year ago",
      "format": "gguf",
      "usage_level": "",
      "usage_active_slots": 0
    },
    {
      "name": "13b-code-q4_K_M",
      "size_bytes": 7900000000,
      "size_text": "7.9GB",
      "context": "16K",
      "input_type": "Text",
      "digest": "0aa12f0144e3",
      "updated": "1 year ago",
      "format": "gguf",
      "usage_level": "",
      "usage_active_slots": 0
    },
    {
      "name": "13b-code-q5_0",
      "size_bytes": 9000000000,
      "size_text": "9.0GB",
      "context": "16K",
      "input_type": "Text",
      "digest": "1a8f4c7a3c5f",
      "updated": "1 year ago",
      "format": "gguf",
      "usage_level": "",
      "usage_active_slots": 0
    },
    {
      "name": "13b-code-q5_1",
      "size_bytes": 9800000000,
      "size_text": "9.8GB",
      "context": "16K",
      "input_type": "Text",
      "digest": "1044f602e601",
      "updated": "1 year ago",
      "format": "gguf",
      "usage_level": "",
      "usage_active_slots": 0
    },
    {
      "name": "13b-code-q5_K_S",
      "size_bytes": 9000000000,
      "size_text": "9.0GB",
      "context": "16K",
      "input_type": "Text",
      "digest": "638856bc2a70",
      "updated": "1 year ago",
      "format": "gguf",
      "usage_level": "",
      "usage_active_slots": 0
    },
    {
      "name": "13b-code-q5_K_M",
      "size_bytes": 9200000000,
      "size_text": "9.2GB",
      "context": "16K",
      "input_type": "Text",
      "digest": "2ed5f2d821a0",
      "updated": "1 year ago",
      "format": "gguf",
      "usage_level": "",
      "usage_active_slots": 0
    },
    {
      "name": "13b-code-q6_K",
      "size_bytes": 11000000000,
      "size_text": "11GB",
      "context": "16K",
      "input_type": "Text",
      "digest": "bbf97c457aa3",
      "updated": "1 year ago",
      "format": "gguf",
      "usage_level": "",
      "usage_active_slots": 0
    },
    {
      "name": "13b-code-q8_0",
      "size_bytes": 14000000000,
      "size_text": "14GB",
      "context": "16K",
      "input_type": "Text",
      "digest": "03674985089a",
      "updated": "1 year ago",
      "format": "gguf",
      "usage_level": "",
      "usage_active_slots": 0
    },
    {
      "name": "13b-code-fp16",
      "size_bytes": 26000000000,
      "size_text": "26GB",
      "context": "16K",
      "input_type": "Text",
      "digest": "d2d1857cd78a",
      "updated": "1 year ago",
      "format": "gguf",
      "usage_level": "",
      "usage_active_slots": 0
    },
    {
      "name": "13b-instruct",
      "size_bytes": 7400000000,
      "size_text": "7.4GB",
      "context": "16K",
      "input_type": "Text",
      "digest": "9f438cb9cd58",
      "updated": "2 years ago",
      "format": "gguf",
      "usage_level": "",
      "usage_active_slots": 0
    },
    {
      "name": "13b-instruct-q2_K",
      "size_bytes": 5400000000,
      "size_text": "5.4GB",
      "context": "16K",
      "input_type": "Text",
      "digest": "8fb59331633d",
      "updated": "2 years ago",
      "format": "gguf",
      "usage_level": "",
      "usage_active_slots": 0
    },
    {
      "name": "13b-instruct-q3_K_S",
      "size_bytes": 5700000000,
      "size_text": "5.7GB",
      "context": "16K",
      "input_type": "Text",
      "digest": "c67eb99f3c22",
      "updated": "2 years ago",
      "format": "gguf",
      "usage_level": "",
      "usage_active_slots": 0
    },
    {
      "name": "13b-instruct-q3_K_M",
      "size_bytes": 6300000000,
      "size_text": "6.3GB",
      "context": "16K",
      "input_type": "Text",
      "digest": "b6cfa4228952",
      "updated": "2 years ago",
      "format": "gguf",
      "usage_level": "",
      "usage_active_slots": 0
    },
    {
      "name": "13b-instruct-q3_K_L",
      "size_bytes": 6900000000,
      "size_text": "6.9GB",
      "context": "16K",
      "input_type": "Text",
      "digest": "bce5c62dfd7d",
      "updated": "2 years ago",
      "format": "gguf",
      "usage_level": "",
      "usage_active_slots": 0
    },
    {
      "name": "13b-instruct-q4_0",
      "size_bytes": 7400000000,
      "size_text": "7.4GB",
      "context": "16K",
      "input_type": "Text",
      "digest": "9f438cb9cd58",
      "updated": "2 years ago",
      "format": "gguf",
      "usage_level": "",
      "usage_active_slots": 0
    },
    {
      "name": "13b-instruct-q4_1",
      "size_bytes": 8199999999,
      "size_text": "8.2GB",
      "context": "16K",
      "input_type": "Text",
      "digest": "e41f7cfb904d",
      "updated": "2 years ago",
      "format": "gguf",
      "usage_level": "",
      "usage_active_slots": 0
    },
    {
      "name": "13b-instruct-q4_K_S",
      "size_bytes": 7400000000,
      "size_text": "7.4GB",
      "context": "16K",
      "input_type": "Text",
      "digest": "ea05ed122e9e",
      "updated": "2 years ago",
      "format": "gguf",
      "usage_level": "",
      "usage_active_slots": 0
    },
    {
      "name": "13b-instruct-q4_K_M",
      "size_bytes": 7900000000,
      "size_text": "7.9GB",
      "context": "16K",
      "input_type": "Text",
      "digest": "96b64dad9259",
      "updated": "2 years ago",
      "format": "gguf",
      "usage_level": "",
      "usage_active_slots": 0
    },
    {
      "name": "13b-instruct-q5_0",
      "size_bytes": 9000000000,
      "size_text": "9.0GB",
      "context": "16K",
      "input_type": "Text",
      "digest": "272076d850ca",
      "updated": "2 years ago",
      "format": "gguf",
      "usage_level": "",
      "usage_active_slots": 0
    },
    {
      "name": "13b-instruct-q5_1",
      "size_bytes": 9800000000,
      "size_text": "9.8GB",
      "context": "16K",
      "input_type": "Text",
      "digest": "c314aa11a40d",
      "updated": "2 years ago",
      "format": "gguf",
      "usage_level": "",
      "usage_active_slots": 0
    },
    {
      "name": "13b-instruct-q5_K_S",
      "size_bytes": 9000000000,
      "size_text": "9.0GB",
      "context": "16K",
      "input_type": "Text",
      "digest": "88522b510fcb",
      "updated": "2 years ago",
      "format": "gguf",
      "usage_level": "",
      "usage_active_slots": 0
    },
    {
      "name": "13b-instruct-q5_K_M",
      "size_bytes": 9200000000,
      "size_text": "9.2GB",
      "context": "16K",
      "input_type": "Text",
      "digest": "d4a5d7a6ca94",
      "updated": "2 years ago",
      "format": "gguf",
      "usage_level": "",
      "usage_active_slots": 0
    },
    {
      "name": "13b-instruct-q6_K",
      "size_bytes": 11000000000,
      "size_text": "11GB",
      "context": "16K",
      "input_type": "Text",
      "digest": "d0a67452c242",
      "updated": "2 years ago",
      "format": "gguf",
      "usage_level": "",
      "usage_active_slots": 0
    },
    {
      "name": "13b-instruct-q8_0",
      "size_bytes": 14000000000,
      "size_text": "14GB",
      "context": "16K",
      "input_type": "Text",
      "digest": "196822804b09",
      "updated": "2 years ago",
      "format": "gguf",
      "usage_level": "",
      "usage_active_slots": 0
    },
    {
      "name": "13b-instruct-fp16",
      "size_bytes": 26000000000,
      "size_text": "26GB",
      "context": "16K",
      "input_type": "Text",
      "digest": "220d80e5d12b",
      "updated": "2 years ago",
      "format": "gguf",
      "usage_level": "",
      "usage_active_slots": 0
    },
    {
      "name": "13b-python",
      "size_bytes": 7400000000,
      "size_text": "7.4GB",
      "context": "16K",
      "input_type": "Text",
      "digest": "ac95ebf45ada",
      "updated": "2 years ago",
      "format": "gguf",
      "usage_level": "",
      "usage_active_slots": 0
    },
    {
      "name": "13b-python-q2_K",
      "size_bytes": 5400000000,
      "size_text": "5.4GB",
      "context": "16K",
      "input_type": "Text",
      "digest": "c9b35dd8cb12",
      "updated": "2 years ago",
      "format": "gguf",
      "usage_level": "",
      "usage_active_slots": 0
    },
    {
      "name": "13b-python-q3_K_S",
      "size_bytes": 5700000000,
      "size_text": "5.7GB",
      "context": "16K",
      "input_type": "Text",
      "digest": "0b5b459ae6ac",
      "updated": "2 years ago",
      "format": "gguf",
      "usage_level": "",
      "usage_active_slots": 0
    },
    {
      "name": "13b-python-q3_K_M",
      "size_bytes": 6300000000,
      "size_text": "6.3GB",
      "context": "16K",
      "input_type": "Text",
      "digest": "97d666909551",
      "updated": "2 years ago",
      "format": "gguf",
      "usage_level": "",
      "usage_active_slots": 0
    },
    {
      "name": "13b-python-q3_K_L",
      "size_bytes": 6900000000,
      "size_text": "6.9GB",
      "context": "16K",
      "input_type": "Text",
      "digest": "f499608bd8fc",
      "updated": "2 years ago",
      "format": "gguf",
      "usage_level": "",
      "usage_active_slots": 0
    },
    {
      "name": "13b-python-q4_0",
      "size_bytes": 7400000000,
      "size_text": "7.4GB",
      "context": "16K",
      "input_type": "Text",
      "digest": "ac95ebf45ada",
      "updated": "2 years ago",
      "format": "gguf",
      "usage_level": "",
      "usage_active_slots": 0
    },
    {
      "name": "13b-python-q4_1",
      "size_bytes": 8199999999,
      "size_text": "8.2GB",
      "context": "16K",
      "input_type": "Text",
      "digest": "a7e755ca330e",
      "updated": "2 years ago",
      "format": "gguf",
      "usage_level": "",
      "usage_active_slots": 0
    },
    {
      "name": "13b-python-q4_K_S",
      "size_bytes": 7400000000,
      "size_text": "7.4GB",
      "context": "16K",
      "input_type": "Text",
      "digest": "efca725ae5a6",
      "updated": "2 years ago",
      "format": "gguf",
      "usage_level": "",
      "usage_active_slots": 0
    },
    {
      "name": "13b-python-q4_K_M",
      "size_bytes": 7900000000,
      "size_text": "7.9GB",
      "context": "16K",
      "input_type": "Text",
      "digest": "897d6f158bff",
      "updated": "2 years ago",
      "format": "gguf",
      "usage_level": "",
      "usage_active_slots": 0
    },
    {
      "name": "13b-python-q5_0",
      "size_bytes": 9000000000,
      "size_text": "9.0GB",
      "context": "16K",
      "input_type": "Text",
      "digest": "4310a4450fac",
      "updated": "2 years ago",
      "format": "gguf",
      "usage_level": "",
      "usage_active_slots": 0
    },
    {
      "name": "13b-python-q5_1",
      "size_bytes": 9800000000,
      "size_text": "9.8GB",
      "context": "16K",
      "input_type": "Text",
      "digest": "d896d2264b62",
      "updated": "2 years ago",
      "format": "gguf",
      "usage_level": "",
      "usage_active_slots": 0
    },
    {
      "name": "13b-python-q5_K_S",
      "size_bytes": 9000000000,
      "size_text": "9.0GB",
      "context": "16K",
      "input_type": "Text",
      "digest": "23198bde3624",
      "updated": "2 years ago",
      "format": "gguf",
      "usage_level": "",
      "usage_active_slots": 0
    },
    {
      "name": "13b-python-q5_K_M",
      "size_bytes": 9200000000,
      "size_text": "9.2GB",
      "context": "16K",
      "input_type": "Text",
      "digest": "bee3e1199c6e",
      "updated": "2 years ago",
      "format": "gguf",
      "usage_level": "",
      "usage_active_slots": 0
    },
    {
      "name": "13b-python-q6_K",
      "size_bytes": 11000000000,
      "size_text": "11GB",
      "context": "16K",
      "input_type": "Text",
      "digest": "a156022a735c",
      "updated": "2 years ago",
      "format": "gguf",
      "usage_level": "",
      "usage_active_slots": 0
    },
    {
      "name": "13b-python-q8_0",
      "size_bytes": 14000000000,
      "size_text": "14GB",
      "context": "16K",
      "input_type": "Text",
      "digest": "651a360f8207",
      "updated": "2 years ago",
      "format": "gguf",
      "usage_level": "",
      "usage_active_slots": 0
    },
    {
      "name": "13b-python-fp16",
      "size_bytes": 26000000000,
      "size_text": "26GB",
      "context": "16K",
      "input_type": "Text",
      "digest": "46a84a4b71b0",
      "updated": "2 years ago",
      "format": "gguf",
      "usage_level": "",
      "usage_active_slots": 0
    },
    {
      "name": "34b-code",
      "size_bytes": 19000000000,
      "size_text": "19GB",
      "context": "16K",
      "input_type": "Text",
      "digest": "d42f383a80dd",
      "updated": "2 years ago",
      "format": "gguf",
      "usage_level": "",
      "usage_active_slots": 0
    },
    {
      "name": "34b-code-q2_K",
      "size_bytes": 14000000000,
      "size_text": "14GB",
      "context": "16K",
      "input_type": "Text",
      "digest": "a9cbbaa0bc9f",
      "updated": "2 years ago",
      "format": "gguf",
      "usage_level": "",
      "usage_active_slots": 0
    },
    {
      "name": "34b-code-q3_K_S",
      "size_bytes": 15000000000,
      "size_text": "15GB",
      "context": "16K",
      "input_type": "Text",
      "digest": "3c90e44e0e1a",
      "updated": "2 years ago",
      "format": "gguf",
      "usage_level": "",
      "usage_active_slots": 0
    },
    {
      "name": "34b-code-q3_K_M",
      "size_bytes": 16000000000,
      "size_text": "16GB",
      "context": "16K",
      "input_type": "Text",
      "digest": "b2341adf3f23",
      "updated": "2 years ago",
      "format": "gguf",
      "usage_level": "",
      "usage_active_slots": 0
    },
    {
      "name": "34b-code-q3_K_L",
      "size_bytes": 18000000000,
      "size_text": "18GB",
      "context": "16K",
      "input_type": "Text",
      "digest": "aedf79bb4b36",
      "updated": "2 years ago",
      "format": "gguf",
      "usage_level": "",
      "usage_active_slots": 0
    },
    {
      "name": "34b-code-q4_0",
      "size_bytes": 19000000000,
      "size_text": "19GB",
      "context": "16K",
      "input_type": "Text",
      "digest": "d42f383a80dd",
      "updated": "2 years ago",
      "format": "gguf",
      "usage_level": "",
      "usage_active_slots": 0
    },
    {
      "name": "34b-code-q4_1",
      "size_bytes": 21000000000,
      "size_text": "21GB",
      "context": "16K",
      "input_type": "Text",
      "digest": "9fa15ea27404",
      "updated": "2 years ago",
      "format": "gguf",
      "usage_level": "",
      "usage_active_slots": 0
    },
    {
      "name": "34b-code-q4_K_S",
      "size_bytes": 19000000000,
      "size_text": "19GB",
      "context": "16K",
      "input_type": "Text",
      "digest": "74265e6ee37b",
      "updated": "2 years ago",
      "format": "gguf",
      "usage_level": "",
      "usage_active_slots": 0
    },
    {
      "name": "34b-code-q4_K_M",
      "size_bytes": 20000000000,
      "size_text": "20GB",
      "context": "16K",
      "input_type": "Text",
      "digest": "ab557c194836",
      "updated": "2 years ago",
      "format": "gguf",
      "usage_level": "",
      "usage_active_slots": 0
    },
    {
      "name": "34b-code-q5_0",
      "size_bytes": 23000000000,
      "size_text": "23GB",
      "context": "16K",
      "input_type": "Text",
      "digest": "1024c60168c2",
      "updated": "2 years ago",
      "format": "gguf",
      "usage_level": "",
      "usage_active_slots": 0
    },
    {
      "name": "34b-code-q5_1",
      "size_bytes": 25000000000,
      "size_text": "25GB",
      "context": "16K",
      "input_type": "Text",
      "digest": "53011c2b63fa",
      "updated": "2 years ago",
      "format": "gguf",
      "usage_level": "",
      "usage_active_slots": 0
    },
    {
      "name": "34b-code-q5_K_S",
      "size_bytes": 23000000000,
      "size_text": "23GB",
      "context": "16K",
      "input_type": "Text",
      "digest": "31fd37f72149",
      "updated": "2 years ago",
      "format": "gguf",
      "usage_level": "",
      "usage_active_slots": 0
    },
    {
      "name": "34b-code-q5_K_M",
      "size_bytes": 24000000000,
      "size_text": "24GB",
      "context": "16K",
      "input_type": "Text",
      "digest": "64ead69c55e3",
      "updated": "2 years ago",
      "format": "gguf",
      "usage_level": "",
      "usage_active_slots": 0
    },
    {
      "name": "34b-code-q6_K",
      "size_bytes": 28000000000,
      "size_text": "28GB",
      "context": "16K",
      "input_type": "Text",
      "digest": "16cab6eea3fc",
      "updated": "2 years ago",
      "format": "gguf",
      "usage_level": "",
      "usage_active_slots": 0
    },
    {
      "name": "34b-code-q8_0",
      "size_bytes": 36000000000,
      "size_text": "36GB",
      "context": "16K",
      "input_type": "Text",
      "digest": "9002fe264a7a",
      "updated": "2 years ago",
      "format": "gguf",
      "usage_level": "",
      "usage_active_slots": 0
    },
    {
      "name": "34b-instruct",
      "size_bytes": 19000000000,
      "size_text": "19GB",
      "context": "16K",
      "input_type": "Text",
      "digest": "685be00e1532",
      "updated": "2 years ago",
      "format": "gguf",
      "usage_level": "",
      "usage_active_slots": 0
    },
    {
      "name": "34b-instruct-q2_K",
      "size_bytes": 14000000000,
      "size_text": "14GB",
      "context": "16K",
      "input_type": "Text",
      "digest": "1dd65b85730e",
      "updated": "2 years ago",
      "format": "gguf",
      "usage_level": "",
      "usage_active_slots": 0
    },
    {
      "name": "34b-instruct-q3_K_S",
      "size_bytes": 15000000000,
      "size_text": "15GB",
      "context": "16K",
      "input_type": "Text",
      "digest": "97ab8a9c3b5b",
      "updated": "2 years ago",
      "format": "gguf",
      "usage_level": "",
      "usage_active_slots": 0
    },
    {
      "name": "34b-instruct-q3_K_M",
      "size_bytes": 16000000000,
      "size_text": "16GB",
      "context": "16K",
      "input_type": "Text",
      "digest": "f534f618ea64",
      "updated": "2 years ago",
      "format": "gguf",
      "usage_level": "",
      "usage_active_slots": 0
    },
    {
      "name": "34b-instruct-q3_K_L",
      "size_bytes": 18000000000,
      "size_text": "18GB",
      "context": "16K",
      "input_type": "Text",
      "digest": "ddb843faeaf7",
      "updated": "2 years ago",
      "format": "gguf",
      "usage_level": "",
      "usage_active_slots": 0
    },
    {
      "name": "34b-instruct-q4_0",
      "size_bytes": 19000000000,
      "size_text": "19GB",
      "context": "16K",
      "input_type": "Text",
      "digest": "685be00e1532",
      "updated": "2 years ago",
      "format": "gguf",
      "usage_level": "",
      "usage_active_slots": 0
    },
    {
      "name": "34b-instruct-q4_1",
      "size_bytes": 21000000000,
      "size_text": "21GB",
      "context": "16K",
      "input_type": "Text",
      "digest": "5493004f889d",
      "updated": "2 years ago",
      "format": "gguf",
      "usage_level": "",
      "usage_active_slots": 0
    },
    {
      "name": "34b-instruct-q4_K_S",
      "size_bytes": 19000000000,
      "size_text": "19GB",
      "context": "16K",
      "input_type": "Text",
      "digest": "9ed594b9bf24",
      "updated": "2 years ago",
      "format": "gguf",
      "usage_level": "",
      "usage_active_slots": 0
    },
    {
      "name": "34b-instruct-q4_K_M",
      "size_bytes": 20000000000,
      "size_text": "20GB",
      "context": "16K",
      "input_type": "Text",
      "digest": "e12e86e65362",
      "updated": "2 years ago",
      "format": "gguf",
      "usage_level": "",
      "usage_active_slots": 0
    },
    {
      "name": "34b-instruct-q5_0",
      "size_bytes": 23000000000,
      "size_text": "23GB",
      "context": "16K",
      "input_type": "Text",
      "digest": "44c793b41643",
      "updated": "2 years ago",
      "format": "gguf",
      "usage_level": "",
      "usage_active_slots": 0
    },
    {
      "name": "34b-instruct-q5_1",
      "size_bytes": 25000000000,
      "size_text": "25GB",
      "context": "16K",
      "input_type": "Text",
      "digest": "b0615499241e",
      "updated": "2 years ago",
      "format": "gguf",
      "usage_level": "",
      "usage_active_slots": 0
    },
    {
      "name": "34b-instruct-q5_K_S",
      "size_bytes": 23000000000,
      "size_text": "23GB",
      "context": "16K",
      "input_type": "Text",
      "digest": "cd41440962fd",
      "updated": "2 years ago",
      "format": "gguf",
      "usage_level": "",
      "usage_active_slots": 0
    },
    {
      "name": "34b-instruct-q5_K_M",
      "size_bytes": 24000000000,
      "size_text": "24GB",
      "context": "16K",
      "input_type": "Text",
      "digest": "93723cb9e26c",
      "updated": "2 years ago",
      "format": "gguf",
      "usage_level": "",
      "usage_active_slots": 0
    },
    {
      "name": "34b-instruct-q6_K",
      "size_bytes": 28000000000,
      "size_text": "28GB",
      "context": "16K",
      "input_type": "Text",
      "digest": "e93676fdc8e4",
      "updated": "2 years ago",
      "format": "gguf",
      "usage_level": "",
      "usage_active_slots": 0
    },
    {
      "name": "34b-instruct-q8_0",
      "size_bytes": 36000000000,
      "size_text": "36GB",
      "context": "16K",
      "input_type": "Text",
      "digest": "df46def864c6",
      "updated": "2 years ago",
      "format": "gguf",
      "usage_level": "",
      "usage_active_slots": 0
    },
    {
      "name": "34b-instruct-fp16",
      "size_bytes": 67000000000,
      "size_text": "67GB",
      "context": "16K",
      "input_type": "Text",
      "digest": "63f5f2314d06",
      "updated": "2 years ago",
      "format": "gguf",
      "usage_level": "",
      "usage_active_slots": 0
    },
    {
      "name": "34b-python",
      "size_bytes": 19000000000,
      "size_text": "19GB",
      "context": "16K",
      "input_type": "Text",
      "digest": "a9991b91af79",
      "updated": "2 years ago",
      "format": "gguf",
      "usage_level": "",
      "usage_active_slots": 0
    },
    {
      "name": "34b-python-q2_K",
      "size_bytes": 14000000000,
      "size_text": "14GB",
      "context": "16K",
      "input_type": "Text",
      "digest": "804f8d3619ca",
      "updated": "2 years ago",
      "format": "gguf",
      "usage_level": "",
      "usage_active_slots": 0
    },
    {
      "name": "34b-python-q3_K_S",
      "size_bytes": 15000000000,
      "size_text": "15GB",
      "context": "16K",
      "input_type": "Text",
      "digest": "7d04d3730258",
      "updated": "2 years ago",
      "format": "gguf",
      "usage_level": "",
      "usage_active_slots": 0
    },
    {
      "name": "34b-python-q3_K_M",
      "size_bytes": 16000000000,
      "size_text": "16GB",
      "context": "16K",
      "input_type": "Text",
      "digest": "4d1f7919eac7",
      "updated": "2 years ago",
      "format": "gguf",
      "usage_level": "",
      "usage_active_slots": 0
    },
    {
      "name": "34b-python-q3_K_L",
      "size_bytes": 18000000000,
      "size_text": "18GB",
      "context": "16K",
      "input_type": "Text",
      "digest": "9a0962344498",
      "updated": "2 years ago",
      "format": "gguf",
      "usage_level": "",
      "usage_active_slots": 0
    },
    {
      "name": "34b-python-q4_0",
      "size_bytes": 19000000000,
      "size_text": "19GB",
      "context": "16K",
      "input_type": "Text",
      "digest": "a9991b91af79",
      "updated": "2 years ago",
      "format": "gguf",
      "usage_level": "",
      "usage_active_slots": 0
    },
    {
      "name": "34b-python-q4_1",
      "size_bytes": 21000000000,
      "size_text": "21GB",
      "context": "16K",
      "input_type": "Text",
      "digest": "a1d4355844ab",
      "updated": "2 years ago",
      "format": "gguf",
      "usage_level": "",
      "usage_active_slots": 0
    },
    {
      "name": "34b-python-q4_K_S",
      "size_bytes": 19000000000,
      "size_text": "19GB",
      "context": "16K",
      "input_type": "Text",
      "digest": "dbf6c5ef8774",
      "updated": "2 years ago",
      "format": "gguf",
      "usage_level": "",
      "usage_active_slots": 0
    },
    {
      "name": "34b-python-q4_K_M",
      "size_bytes": 20000000000,
      "size_text": "20GB",
      "context": "16K",
      "input_type": "Text",
      "digest": "4c63b99ce6e0",
      "updated": "2 years ago",
      "format": "gguf",
      "usage_level": "",
      "usage_active_slots": 0
    },
    {
      "name": "34b-python-q5_0",
      "size_bytes": 23000000000,
      "size_text": "23GB",
      "context": "16K",
      "input_type": "Text",
      "digest": "a8afc91dd7c1",
      "updated": "2 years ago",
      "format": "gguf",
      "usage_level": "",
      "usage_active_slots": 0
    },
    {
      "name": "34b-python-q5_1",
      "size_bytes": 25000000000,
      "size_text": "25GB",
      "context": "16K",
      "input_type": "Text",
      "digest": "2d27ad19cb5e",
      "updated": "2 years ago",
      "format": "gguf",
      "usage_level": "",
      "usage_active_slots": 0
    },
    {
      "name": "34b-python-q5_K_S",
      "size_bytes": 23000000000,
      "size_text": "23GB",
      "context": "16K",
      "input_type": "Text",
      "digest": "893daae3384e",
      "updated": "2 years ago",
      "format": "gguf",
      "usage_level": "",
      "usage_active_slots": 0
    },
    {
      "name": "34b-python-q5_K_M",
      "size_bytes": 24000000000,
      "size_text": "24GB",
      "context": "16K",
      "input_type": "Text",
      "digest": "c6a7e8f2a374",
      "updated": "2 years ago",
      "format": "gguf",
      "usage_level": "",
      "usage_active_slots": 0
    },
    {
      "name": "34b-python-q6_K",
      "size_bytes": 28000000000,
      "size_text": "28GB",
      "context": "16K",
      "input_type": "Text",
      "digest": "4c08957e57e2",
      "updated": "2 years ago",
      "format": "gguf",
      "usage_level": "",
      "usage_active_slots": 0
    },
    {
      "name": "34b-python-q8_0",
      "size_bytes": 36000000000,
      "size_text": "36GB",
      "context": "16K",
      "input_type": "Text",
      "digest": "53a286016fd9",
      "updated": "2 years ago",
      "format": "gguf",
      "usage_level": "",
      "usage_active_slots": 0
    },
    {
      "name": "34b-python-fp16",
      "size_bytes": 67000000000,
      "size_text": "67GB",
      "context": "16K",
      "input_type": "Text",
      "digest": "a12bdba154f9",
      "updated": "2 years ago",
      "format": "gguf",
      "usage_level": "",
      "usage_active_slots": 0
    },
    {
      "name": "70b-code",
      "size_bytes": 39000000000,
      "size_text": "39GB",
      "context": "16K",
      "input_type": "Text",
      "digest": "f51f75d243f2",
      "updated": "2 years ago",
      "format": "gguf",
      "usage_level": "",
      "usage_active_slots": 0
    },
    {
      "name": "70b-code-q2_K",
      "size_bytes": 25000000000,
      "size_text": "25GB",
      "context": "16K",
      "input_type": "Text",
      "digest": "a971fcfd33e2",
      "updated": "2 years ago",
      "format": "gguf",
      "usage_level": "",
      "usage_active_slots": 0
    },
    {
      "name": "70b-code-q3_K_S",
      "size_bytes": 30000000000,
      "size_text": "30GB",
      "context": "16K",
      "input_type": "Text",
      "digest": "6f9fcc129873",
      "updated": "2 years ago",
      "format": "gguf",
      "usage_level": "",
      "usage_active_slots": 0
    },
    {
      "name": "70b-code-q3_K_M",
      "size_bytes": 33000000000,
      "size_text": "33GB",
      "context": "16K",
      "input_type": "Text",
      "digest": "d29df36f0809",
      "updated": "2 years ago",
      "format": "gguf",
      "usage_level": "",
      "usage_active_slots": 0
    },
    {
      "name": "70b-code-q3_K_L",
      "size_bytes": 36000000000,
      "size_text": "36GB",
      "context": "16K",
      "input_type": "Text",
      "digest": "4bfb484bdd00",
      "updated": "2 years ago",
      "format": "gguf",
      "usage_level": "",
      "usage_active_slots": 0
    },
    {
      "name": "70b-code-q4_0",
      "size_bytes": 39000000000,
      "size_text": "39GB",
      "context": "16K",
      "input_type": "Text",
      "digest": "f51f75d243f2",
      "updated": "2 years ago",
      "format": "gguf",
      "usage_level": "",
      "usage_active_slots": 0
    },
    {
      "name": "70b-code-q4_1",
      "size_bytes": 43000000000,
      "size_text": "43GB",
      "context": "16K",
      "input_type": "Text",
      "digest": "f4f87b75ed5f",
      "updated": "2 years ago",
      "format": "gguf",
      "usage_level": "",
      "usage_active_slots": 0
    },
    {
      "name": "70b-code-q4_K_S",
      "size_bytes": 39000000000,
      "size_text": "39GB",
      "context": "16K",
      "input_type": "Text",
      "digest": "6eb3eed1c7d7",
      "updated": "2 years ago",
      "format": "gguf",
      "usage_level": "",
      "usage_active_slots": 0
    },
    {
      "name": "70b-code-q4_K_M",
      "size_bytes": 41000000000,
      "size_text": "41GB",
      "context": "16K",
      "input_type": "Text",
      "digest": "af49f7163a95",
      "updated": "2 years ago",
      "format": "gguf",
      "usage_level": "",
      "usage_active_slots": 0
    },
    {
      "name": "70b-code-q5_0",
      "size_bytes": 47000000000,
      "size_text": "47GB",
      "context": "16K",
      "input_type": "Text",
      "digest": "6c13a8df97a6",
      "updated": "2 years ago",
      "format": "gguf",
      "usage_level": "",
      "usage_active_slots": 0
    },
    {
      "name": "70b-code-q5_1",
      "size_bytes": 52000000000,
      "size_text": "52GB",
      "context": "16K",
      "input_type": "Text",
      "digest": "d81dfb4ec245",
      "updated": "2 years ago",
      "format": "gguf",
      "usage_level": "",
      "usage_active_slots": 0
    },
    {
      "name": "70b-code-q5_K_S",
      "size_bytes": 47000000000,
      "size_text": "47GB",
      "context": "16K",
      "input_type": "Text",
      "digest": "f7a6b036969c",
      "updated": "2 years ago",
      "format": "gguf",
      "usage_level": "",
      "usage_active_slots": 0
    },
    {
      "name": "70b-code-q5_K_M",
      "size_bytes": 49000000000,
      "size_text": "49GB",
      "context": "16K",
      "input_type": "Text",
      "digest": "a6de2758bbb4",
      "updated": "2 years ago",
      "format": "gguf",
      "usage_level": "",
      "usage_active_slots": 0
    },
    {
      "name": "70b-code-q6_K",
      "size_bytes": 57000000000,
      "size_text": "57GB",
      "context": "16K",
      "input_type": "Text",
      "digest": "8fe5090ef2aa",
      "updated": "2 years ago",
      "format": "gguf",
      "usage_level": "",
      "usage_active_slots": 0
    },
    {
      "name": "70b-code-q8_0",
      "size_bytes": 73000000000,
      "size_text": "73GB",
      "context": "16K",
      "input_type": "Text",
      "digest": "11ccdd14d3a7",
      "updated": "2 years ago",
      "format": "gguf",
      "usage_level": "",
      "usage_active_slots": 0
    },
    {
      "name": "70b-code-fp16",
      "size_bytes": 138000000000,
      "size_text": "138GB",
      "context": "16K",
      "input_type": "Text",
      "digest": "068561d5fd67",
      "updated": "2 years ago",
      "format": "gguf",
      "usage_level": "",
      "usage_active_slots": 0
    },
    {
      "name": "70b-instruct",
      "size_bytes": 39000000000,
      "size_text": "39GB",
      "context": "2K",
      "input_type": "Text",
      "digest": "e59b580dfce7",
      "updated": "2 years ago",
      "format": "gguf",
      "usage_level": "",
      "usage_active_slots": 0
    },
    {
      "name": "70b-instruct-q2_K",
      "size_bytes": 25000000000,
      "size_text": "25GB",
      "context": "2K",
      "input_type": "Text",
      "digest": "cfb9810598f2",
      "updated": "2 years ago",
      "format": "gguf",
      "usage_level": "",
      "usage_active_slots": 0
    },
    {
      "name": "70b-instruct-q3_K_S",
      "size_bytes": 30000000000,
      "size_text": "30GB",
      "context": "2K",
      "input_type": "Text",
      "digest": "9eaafc67a1e9",
      "updated": "2 years ago",
      "format": "gguf",
      "usage_level": "",
      "usage_active_slots": 0
    },
    {
      "name": "70b-instruct-q3_K_M",
      "size_bytes": 33000000000,
      "size_text": "33GB",
      "context": "2K",
      "input_type": "Text",
      "digest": "97d27e87a494",
      "updated": "2 years ago",
      "format": "gguf",
      "usage_level": "",
      "usage_active_slots": 0
    },
    {
      "name": "70b-instruct-q3_K_L",
      "size_bytes": 36000000000,
      "size_text": "36GB",
      "context": "2K",
      "input_type": "Text",
      "digest": "9b7b348bd092",
      "updated": "2 years ago",
      "format": "gguf",
      "usage_level": "",
      "usage_active_slots": 0
    },
    {
      "name": "70b-instruct-q4_0",
      "size_bytes": 39000000000,
      "size_text": "39GB",
      "context": "2K",
      "input_type": "Text",
      "digest": "e59b580dfce7",
      "updated": "2 years ago",
      "format": "gguf",
      "usage_level": "",
      "usage_active_slots": 0
    },
    {
      "name": "70b-instruct-q4_1",
      "size_bytes": 43000000000,
      "size_text": "43GB",
      "context": "2K",
      "input_type": "Text",
      "digest": "3a050fe20496",
      "updated": "2 years ago",
      "format": "gguf",
      "usage_level": "",
      "usage_active_slots": 0
    },
    {
      "name": "70b-instruct-q4_K_S",
      "size_bytes": 39000000000,
      "size_text": "39GB",
      "context": "2K",
      "input_type": "Text",
      "digest": "5e6f76df85f1",
      "updated": "2 years ago",
      "format": "gguf",
      "usage_level": "",
      "usage_active_slots": 0
    },
    {
      "name": "70b-instruct-q4_K_M",
      "size_bytes": 41000000000,
      "size_text": "41GB",
      "context": "2K",
      "input_type": "Text",
      "digest": "fd3eb0359236",
      "updated": "2 years ago",
      "format": "gguf",
      "usage_level": "",
      "usage_active_slots": 0
    },
    {
      "name": "70b-instruct-q5_0",
      "size_bytes": 47000000000,
      "size_text": "47GB",
      "context": "2K",
      "input_type": "Text",
      "digest": "b22318ff25f3",
      "updated": "2 years ago",
      "format": "gguf",
      "usage_level": "",
      "usage_active_slots": 0
    },
    {
      "name": "70b-instruct-q5_1",
      "size_bytes": 52000000000,
      "size_text": "52GB",
      "context": "2K",
      "input_type": "Text",
      "digest": "5606d0558a97",
      "updated": "2 years ago",
      "format": "gguf",
      "usage_level": "",
      "usage_active_slots": 0
    },
    {
      "name": "70b-instruct-q5_K_S",
      "size_bytes": 47000000000,
      "size_text": "47GB",
      "context": "2K",
      "input_type": "Text",
      "digest": "486ce7f5c313",
      "updated": "2 years ago",
      "format": "gguf",
      "usage_level": "",
      "usage_active_slots": 0
    },
    {
      "name": "70b-instruct-q5_K_M",
      "size_bytes": 49000000000,
      "size_text": "49GB",
      "context": "2K",
      "input_type": "Text",
      "digest": "796aa29c1e74",
      "updated": "2 years ago",
      "format": "gguf",
      "usage_level": "",
      "usage_active_slots": 0
    },
    {
      "name": "70b-instruct-q6_K",
      "size_bytes": 57000000000,
      "size_text": "57GB",
      "context": "4K",
      "input_type": "Text",
      "digest": "2b057a1a5fcb",
      "updated": "2 years ago",
      "format": "gguf",
      "usage_level": "",
      "usage_active_slots": 0
    },
    {
      "name": "70b-instruct-q8_0",
      "size_bytes": 73000000000,
      "size_text": "73GB",
      "context": "2K",
      "input_type": "Text",
      "digest": "df2a96247c0c",
      "updated": "2 years ago",
      "format": "gguf",
      "usage_level": "",
      "usage_active_slots": 0
    },
    {
      "name": "70b-instruct-fp16",
      "size_bytes": 138000000000,
      "size_text": "138GB",
      "context": "4K",
      "input_type": "Text",
      "digest": "bbea3b24dc4b",
      "updated": "2 years ago",
      "format": "gguf",
      "usage_level": "",
      "usage_active_slots": 0
    },
    {
      "name": "70b-python",
      "size_bytes": 39000000000,
      "size_text": "39GB",
      "context": "4K",
      "input_type": "Text",
      "digest": "33bc097b32fe",
      "updated": "2 years ago",
      "format": "gguf",
      "usage_level": "",
      "usage_active_slots": 0
    },
    {
      "name": "70b-python-q2_K",
      "size_bytes": 25000000000,
      "size_text": "25GB",
      "context": "4K",
      "input_type": "Text",
      "digest": "8925059dfc69",
      "updated": "2 years ago",
      "format": "gguf",
      "usage_level": "",
      "usage_active_slots": 0
    },
    {
      "name": "70b-python-q3_K_S",
      "size_bytes": 30000000000,
      "size_text": "30GB",
      "context": "4K",
      "input_type": "Text",
      "digest": "5e2c02668fd0",
      "updated": "2 years ago",
      "format": "gguf",
      "usage_level": "",
      "usage_active_slots": 0
    },
    {
      "name": "70b-python-q3_K_M",
      "size_bytes": 33000000000,
      "size_text": "33GB",
      "context": "4K",
      "input_type": "Text",
      "digest": "130b1c22d82c",
      "updated": "2 years ago",
      "format": "gguf",
      "usage_level": "",
      "usage_active_slots": 0
    },
    {
      "name": "70b-python-q3_K_L",
      "size_bytes": 36000000000,
      "size_text": "36GB",
      "context": "4K",
      "input_type": "Text",
      "digest": "91ac3677083b",
      "updated": "2 years ago",
      "format": "gguf",
      "usage_level": "",
      "usage_active_slots": 0
    },
    {
      "name": "70b-python-q4_0",
      "size_bytes": 39000000000,
      "size_text": "39GB",
      "context": "4K",
      "input_type": "Text",
      "digest": "33bc097b32fe",
      "updated": "2 years ago",
      "format": "gguf",
      "usage_level": "",
      "usage_active_slots": 0
    },
    {
      "name": "70b-python-q4_1",
      "size_bytes": 43000000000,
      "size_text": "43GB",
      "context": "4K",
      "input_type": "Text",
      "digest": "8a1b64a13e07",
      "updated": "2 years ago",
      "format": "gguf",
      "usage_level": "",
      "usage_active_slots": 0
    },
    {
      "name": "70b-python-q4_K_S",
      "size_bytes": 39000000000,
      "size_text": "39GB",
      "context": "4K",
      "input_type": "Text",
      "digest": "58f06c520da4",
      "updated": "2 years ago",
      "format": "gguf",
      "usage_level": "",
      "usage_active_slots": 0
    },
    {
      "name": "70b-python-q4_K_M",
      "size_bytes": 41000000000,
      "size_text": "41GB",
      "context": "4K",
      "input_type": "Text",
      "digest": "157bddfb9b58",
      "updated": "2 years ago",
      "format": "gguf",
      "usage_level": "",
      "usage_active_slots": 0
    },
    {
      "name": "70b-python-q5_0",
      "size_bytes": 47000000000,
      "size_text": "47GB",
      "context": "4K",
      "input_type": "Text",
      "digest": "e91924e35649",
      "updated": "2 years ago",
      "format": "gguf",
      "usage_level": "",
      "usage_active_slots": 0
    },
    {
      "name": "70b-python-q5_1",
      "size_bytes": 52000000000,
      "size_text": "52GB",
      "context": "4K",
      "input_type": "Text",
      "digest": "726a52d85424",
      "updated": "2 years ago",
      "format": "gguf",
      "usage_level": "",
      "usage_active_slots": 0
    },
    {
      "name": "70b-python-q5_K_S",
      "size_bytes": 47000000000,
      "size_text": "47GB",
      "context": "4K",
      "input_type": "Text",
      "digest": "b1f1fd5a9237",
      "updated": "2 years ago",
      "format": "gguf",
      "usage_level": "",
      "usage_active_slots": 0
    },
    {
      "name": "70b-python-q5_K_M",
      "size_bytes": 49000000000,
      "size_text": "49GB",
      "context": "4K",
      "input_type": "Text",
      "digest": "46e0203b5440",
      "updated": "2 years ago",
      "format": "gguf",
      "usage_level": "",
      "usage_active_slots": 0
    },
    {
      "name": "70b-python-q6_K",
      "size_bytes": 57000000000,
      "size_text": "57GB",
      "context": "4K",
      "input_type": "Text",
      "digest": "0d2f71fce49d",
      "updated": "2 years ago",
      "format": "gguf",
      "usage_level": "",
      "usage_active_slots": 0
    },
    {
      "name": "70b-python-q8_0",
      "size_bytes": 73000000000,
      "size_text": "73GB",
      "context": "4K",
      "input_type": "Text",
      "digest": "80366d5e2306",
      "updated": "2 years ago",
      "format": "gguf",
      "usage_level": "",
      "usage_active_slots": 0
    },
    {
      "name": "70b-python-fp16",
      "size_bytes": 138000000000,
      "size_text": "138GB",
      "context": "4K",
      "input_type": "Text",
      "digest": "32aef34ce6d1",
      "updated": "2 years ago",
      "format": "gguf",
      "usage_level": "",
      "usage_active_slots": 0
    }
  ]
}